<?xml version="1.0" encoding="UTF-8"?>
<entity-mappings version="2.0"
	xmlns="http://java.sun.com/xml/ns/persistence/orm" xmlns:xsi="http://www.w3.org/2001/XMLSchema-instance"
	xsi:schemaLocation="http://java.sun.com/xml/ns/persistence/orm http://java.sun.com/xml/ns/persistence/orm_2_0.xsd">

	<entity class="at.ac.tuwien.ase2016.wm.model.Sensor" />
	<entity class="at.ac.tuwien.ase2016.wm.model.SensorAlert"/>
	<entity class="at.ac.tuwien.ase2016.wm.model.SensorGroup"/>
	<entity class="at.ac.tuwien.ase2016.wm.model.SensorAggregateEvent"/>
	<entity class="at.ac.tuwien.ase2016.wm.model.SensorStreamEvent"/>
	<entity class="at.ac.tuwien.ase2016.wm.model.SensorStreamInsertEvent"/>
	<entity class="at.ac.tuwien.ase2016.wm.model.Customer" />

	<!-- Only used for the workaround -->
	<entity class="at.ac.tuwien.ase2016.wm.model.workaround.BadQualitySensorEventAggregation"/>
	
</entity-mappings>
